pyrockmodulus/__init__.py
pyrockmodulus/formatting_codes.py
pyrockmodulus/pyrockmodulus.py
pyrockmodulus/rock_variables.py
pyrockmodulus/ucs_bar_chart_plot.py
pyrockmodulus-0.6.dist-info/METADATA
pyrockmodulus-0.6.dist-info/WHEEL
pyrockmodulus-0.6.dist-info/top_level.txt
pyrockmodulus-0.6.dist-info/RECORD
