Metadata-Version: 2.1
Name: pyrockmodulus
Version: 0.6
Summary: Module to plot Modulus and Strength ratios for rock.
Home-page: https://github.com/alicarlos/digital_modulus_strength_ratio
Author: Grasselli's Geomechanics Group - University of Toronto
Author-email: aly.abdelaziz@mail.utoronto.ca
Keywords: Modulus_Ratio Strength_Ratio Deere_Miller Rock_Classification
Requires-Python: >=3.5
Requires-Dist: pandas (>=0.0)
Requires-Dist: numpy (>=1.0)
Requires-Dist: scipy (>=1.2.1)
Requires-Dist: matplotlib (>=3.5)
Requires-Dist: seaborn (>=0.11.0)
